lib_pos.dylib
poseidon_py/c_bindings.py
poseidon_py/__init__.py
poseidon_py/poseidon_hash.py
poseidon_py/utils.py
poseidon_py-0.1.5.dist-info/RECORD
poseidon_py-0.1.5.dist-info/WHEEL
poseidon_py-0.1.5.dist-info/top_level.txt
poseidon_py-0.1.5.dist-info/METADATA
