Metadata-Version: 2.1
Name: poseidon_py
Version: 0.1.5
Summary: Python implementation of Poseidon hash
Home-page: https://github.com/drknzz/poseidon-py.git
Author: drknzz
Author-email: kamil.jankowski.x@gmail.com
Requires-Python: >=3.8
